anchio_sdk/__init__.py
anchio_sdk/exceptions.py
anchio_sdk/main.py
anchio_sdk/types.py
anchio-0.1.2.dist-info/LICENSE
anchio-0.1.2.dist-info/METADATA
anchio-0.1.2.dist-info/WHEEL
anchio-0.1.2.dist-info/RECORD
